vmdcli/__init__.py
vmdcli/_version.py
vmdcli/cli.py
vmdcli/vmdcli.py
vmdcli-0.2.3.dist-info/AUTHORS.md
vmdcli-0.2.3.dist-info/LICENSE
vmdcli-0.2.3.dist-info/METADATA
vmdcli-0.2.3.dist-info/WHEEL
vmdcli-0.2.3.dist-info/entry_points.txt
vmdcli-0.2.3.dist-info/top_level.txt
vmdcli-0.2.3.dist-info/RECORD
