Metadata-Version: 2.1
Name: vmdcli
Version: 0.2.3
Summary: Ce projet est un petit outil en ligne de commande, permettant de détecter les rendez-vous disponibles dans votre département pour recevoir un vaccin contre la covid19.
Home-page: https://github.com/lrivallain/vmdcli
Author: Ludovic Rivallain
License: MIT license
Keywords: vmdcli
Platform: UNKNOWN
Classifier: Development Status :: 2 - Pre-Alpha
Classifier: Intended Audience :: Developers
Classifier: License :: OSI Approved :: MIT License
Classifier: Natural Language :: English
Classifier: Programming Language :: Python :: 3.6
Classifier: Programming Language :: Python :: 3.7
Classifier: Programming Language :: Python :: 3.8
Requires-Python: >=3.6
Requires-Dist: click
Requires-Dist: requests
Requires-Dist: pytz
Requires-Dist: humanize
Requires-Dist: pushbullet.py
Requires-Dist: python-dateutil
